{
	"backtrace" : 3,
	"backtraceGraph" : 
	{
		"commands" : 
		[
			"add_custom_target",
			"gtsamAddTestsGlob_impl",
			"gtsamAddTestsGlob",
			"add_dependencies"
		],
		"files" : 
		[
			"lib/gtsam/cmake/GtsamTesting.cmake",
			"lib/gtsam/gtsam/inference/tests/CMakeLists.txt"
		],
		"nodes" : 
		[
			{
				"file" : 1
			},
			{
				"command" : 2,
				"file" : 1,
				"line" : 1,
				"parent" : 0
			},
			{
				"command" : 1,
				"file" : 0,
				"line" : 30,
				"parent" : 1
			},
			{
				"command" : 0,
				"file" : 0,
				"line" : 129,
				"parent" : 2
			},
			{
				"command" : 3,
				"file" : 0,
				"line" : 177,
				"parent" : 2
			},
			{
				"command" : 3,
				"file" : 0,
				"line" : 177,
				"parent" : 2
			},
			{
				"command" : 3,
				"file" : 0,
				"line" : 177,
				"parent" : 2
			},
			{
				"command" : 3,
				"file" : 0,
				"line" : 177,
				"parent" : 2
			},
			{
				"command" : 3,
				"file" : 0,
				"line" : 177,
				"parent" : 2
			}
		]
	},
	"dependencies" : 
	[
		{
			"backtrace" : 4,
			"id" : "testKey::@6844f82f53a243984d66"
		},
		{
			"backtrace" : 5,
			"id" : "testLabeledSymbol::@6844f82f53a243984d66"
		},
		{
			"backtrace" : 6,
			"id" : "testOrdering::@6844f82f53a243984d66"
		},
		{
			"backtrace" : 7,
			"id" : "testSymbol::@6844f82f53a243984d66"
		},
		{
			"backtrace" : 8,
			"id" : "testVariableSlots::@6844f82f53a243984d66"
		}
	],
	"folder" : 
	{
		"name" : "Unit tests"
	},
	"id" : "check.inference::@6844f82f53a243984d66",
	"name" : "check.inference",
	"paths" : 
	{
		"build" : "lib/gtsam/gtsam/inference/tests",
		"source" : "lib/gtsam/gtsam/inference/tests"
	},
	"sourceGroups" : 
	[
		{
			"name" : "",
			"sourceIndexes" : 
			[
				0
			]
		},
		{
			"name" : "CMake Rules",
			"sourceIndexes" : 
			[
				1
			]
		}
	],
	"sources" : 
	[
		{
			"backtrace" : 3,
			"isGenerated" : true,
			"path" : "build/lib/gtsam/gtsam/inference/tests/CMakeFiles/check.inference",
			"sourceGroupIndex" : 0
		},
		{
			"backtrace" : 0,
			"isGenerated" : true,
			"path" : "build/lib/gtsam/gtsam/inference/tests/CMakeFiles/check.inference.rule",
			"sourceGroupIndex" : 1
		}
	],
	"type" : "UTILITY"
}
